cas_client_integration_django/__init__.py
cas_client_integration_django/__version__.py
cas_client_integration_django/middleware/__init__.py
cas_client_integration_django/middleware/token_ticket_authentication.py
cas_client_integration_django-0.0.2.dist-info/DESCRIPTION.rst
cas_client_integration_django-0.0.2.dist-info/METADATA
cas_client_integration_django-0.0.2.dist-info/RECORD
cas_client_integration_django-0.0.2.dist-info/WHEEL
cas_client_integration_django-0.0.2.dist-info/metadata.json
cas_client_integration_django-0.0.2.dist-info/top_level.txt
