Metadata-Version: 2.0
Name: cas-client-integration-django
Version: 0.0.2
Summary: Python CAS Client
Home-page: https://code.dianrong.com/projects/CMDB/repos/python-cas-client
Author: uinin3x
Author-email: xinxin.xu@dianrong.com
License: MIT
Platform: UNKNOWN
Classifier: License :: OSI Approved :: MIT License
Classifier: Programming Language :: Python
Classifier: Programming Language :: Python :: 2.7
Classifier: Programming Language :: Python :: 3
Classifier: Programming Language :: Python :: 3.3
Classifier: Programming Language :: Python :: 3.4
Classifier: Programming Language :: Python :: 3.5
Classifier: Programming Language :: Python :: 3.6
Classifier: Programming Language :: Python :: Implementation :: CPython
Classifier: Programming Language :: Python :: Implementation :: PyPy
Requires-Dist: django
Requires-Dist: jwcrypto
